puppy_mcp-0.1.0.dist-info/licenses/LICENSE
puppy_mcp_server/__init__.py
puppy_mcp_server/__main__.py
puppy_mcp_server/main.py
puppy_mcp-0.1.0.dist-info/METADATA
puppy_mcp-0.1.0.dist-info/WHEEL
puppy_mcp-0.1.0.dist-info/entry_points.txt
puppy_mcp-0.1.0.dist-info/top_level.txt
puppy_mcp-0.1.0.dist-info/RECORD
