Metadata-Version: 2.4
Name: puppy-mcp
Version: 0.1.0
Summary: Add your description here
License: MIT
Classifier: License :: OSI Approved :: MIT License
Classifier: Programming Language :: Python :: 3
Classifier: Operating System :: OS Independent
Requires-Python: >=3.11
License-File: LICENSE
Requires-Dist: fastmcp>=2.12.3
Requires-Dist: requests>=2.25.0
Dynamic: license-file
